{
  "posts": [
    {
      "id": 1,
      "title": "json-server",
      "author": "typicode"
    },
    {
      "id": 6
    },
    {
      "id": 7
    },
    {
      "id": 8
    },
    {
      "id": 9
    },
    {
      "key1": "value1",
      "key2": "value2",
      "id": 10
    },
    {
      "key1": "value1",
      "key2": "value2",
      "id": 11
    },
    {
      "key1": "value1",
      "key2": "value2",
      "id": 12
    }
  ],
  "comments": [
    {
      "id": 1,
      "body": "some comment",
      "postId": 1
    }
  ],
  "profile": {
    "name": "typicode"
  }
}